README.md
setup.py
freecurrencyapi/__init__.py
freecurrencyapi/client.py
freecurrencyapi.egg-info/PKG-INFO
freecurrencyapi.egg-info/SOURCES.txt
freecurrencyapi.egg-info/dependency_links.txt
freecurrencyapi.egg-info/requires.txt
freecurrencyapi.egg-info/top_level.txt