Metadata-Version: 2.1
Name: freecurrencyapi
Version: 0.1.0
Summary: Freecurrencyapi Python Client
Home-page: https://github.com/everapihq/freecurrencyapi-python
Author: Everapi
Author-email: office@everapi.com
License: MIT
Keywords: free currency api,exchange rates,rates api,freecurrencyapi,currency api
Classifier: Development Status :: 4 - Beta
Classifier: Intended Audience :: Developers
Classifier: License :: OSI Approved :: MIT License
Classifier: Operating System :: OS Independent
Classifier: Programming Language :: Python
Classifier: Programming Language :: Python :: 2.7
Classifier: Programming Language :: Python :: 3
Classifier: Programming Language :: Python :: 3.3
Classifier: Programming Language :: Python :: 3.4
Classifier: Programming Language :: Python :: 3.5
Classifier: Programming Language :: Python :: 3.6
Classifier: Programming Language :: Python :: 3.7
Classifier: Programming Language :: Python :: 3.8
Classifier: Programming Language :: Python :: 3.9
Classifier: Topic :: Software Development :: Libraries :: Python Modules
